LICENSE
MANIFEST.in
README.rst
changelog
requirements.txt
setup.py
Rfc_Errata/__init__.py
Rfc_Errata/apply_errata.py
Rfc_Errata/checker.py
Rfc_Errata/run.py
Rfc_Errata/template.py
Rfc_Errata/test.py
Rfc_Errata/utils.py
Rfc_Errata/Template/endnoteTemplate.txt
Rfc_Errata/Template/headnoteTemplate.txt
Rfc_Errata/Template/htmlTemplate.txt
Rfc_Errata/Template/inlineNoteTemplate.txt
Rfc_Errata/Template/sectionNoteTemplate.txt
Rfc_Errata/css/errata-base.css
Rfc_Errata/css/errata-color.css
Rfc_Errata/css/errata-monochrome.css
Rfc_Errata/css/errata-printer.css
Rfc_Errata/css/errata.js
rfc_errata.egg-info/PKG-INFO
rfc_errata.egg-info/SOURCES.txt
rfc_errata.egg-info/dependency_links.txt
rfc_errata.egg-info/entry_points.txt
rfc_errata.egg-info/not-zip-safe
rfc_errata.egg-info/top_level.txt