Metadata-Version: 1.2
Name: rfc-errata
Version: 0.1.4
Summary: Build html files from the text RFCs and the errata database.
Home-page: https://tools.ietf.org/tools/ietfdb/browser/brance/elft/rfc-errata/
Author: Jim Schaad
Author-email: ietf@augustcellars.com
License: Simplified BSD
Keywords: RFC errata
Platform: UNKNOWN
Classifier: Development Status :: 2 - Pre-Alpha
Classifier: Intended Audience :: Other Audience
Classifier: Topic :: Text Processing
Classifier: Topic :: Text Processing :: Markup :: XML
Classifier: License :: OSI Approved :: BSD License
Classifier: Programming Language :: Python :: 3.6
Requires-Python: >=3.3
